bxinth/__init__.py
bxinth/bxinth.py
bxinth/pairs.py
bxinth/setup.py
bxinth/tests.py
bxinth-0.1.2.dist-info/METADATA
bxinth-0.1.2.dist-info/RECORD
bxinth-0.1.2.dist-info/WHEEL
bxinth-0.1.2.dist-info/pbr.json
bxinth-0.1.2.dist-info/top_level.txt
