Metadata-Version: 2.1
Name: bxinth
Version: 0.1.2
Summary: Python lib for bx.in.th market
Home-page: https://github.com/AHAPX/bxin
Author: AHAPX
Author-email: anarchy.b@gmail.com
License: MIT
Download-URL: https://github.com/AHAPX/bxin/archive/v0.1.1.tar.gz
Keywords: crypto,bx,bitcoin
Platform: UNKNOWN
Requires-Dist: pyotp (==2.2.6)
Requires-Dist: requests (==2.18.4)
